valyuta.py
valyuta-0.1.dist-info/WHEEL
valyuta-0.1.dist-info/METADATA
valyuta-0.1.dist-info/RECORD
