Metadata-Version: 2.1
Name: valyuta
Version: 0.1
Summary: 
Author: coderstack404
Author-email: coderstack404@gmail.com
Requires-Python: >=3.8,<4.0
Classifier: Programming Language :: Python :: 3
Classifier: Programming Language :: Python :: 3.8
Classifier: Programming Language :: Python :: 3.9
Classifier: Programming Language :: Python :: 3.10
Requires-Dist: requests (>=2.28.1,<3.0.0)
